<?xml version="1.0" encoding="UTF-8"?>
<xml xmlns="https://developers.google.com/blockly/xml">
   <block type="SetAsset" id="s*Q:kA?20oEXOBv1u,;l" x="141" y="70">
      <value name="asset">
         <block type="Text" id="T0}x^!V.TAXdbj4O_d3Y">
            <field name="text">Controller</field>
         </block>
      </value>
      <next>
         <block type="SendMessage" id="hvZXG7r=0[x8V~DDh`#d">
            <field name="messageType">MQTT</field>
            <value name="messageContent">
               <block type="Text" id="5:qWV%UZYKF^t0A}qP`0">
                  <field name="text">TestUR10</field>
               </block>
            </value>
         </block>
      </next>
   </block>
   <block type="SetAsset" id="Z#T5Tl(M}h,r|~,M0vif" x="141" y="173">
      <value name="asset">
         <block type="Text" id="|/cIDhzUsP!rb2tx6SkP">
            <field name="text">UCI2Ur10</field>
         </block>
      </value>
      <next>
         <block type="OnMessageReceive" id=";,9PN+%_sGPL+m|^#+zK">
            <field name="messageType">MQTT</field>
            <value name="messageContent">
               <block type="Text" id="KgsiTz}DT9A~%?ekrsml">
                  <field name="text">TestUR10</field>
               </block>
            </value>
            <next>
               <block type="Loop" id="IlTpH4F$XBLh7mk0r3JH">
                  <value name="repeat">
                     <block type="Text" id="[jrc80A!)O_?q8Q6!pqm">
                        <field name="text">X=6</field>
                     </block>
                  </value>
                  <statement name="statement">
                     <block type="Selection" id="U2|QRhHGrw:6Y)/mnQ:[">
                        <value name="condition">
                           <block type="Text" id="2^,%e!45:1Z^1@c96{Oj">
                              <field name="text">X=1</field>
                           </block>
                        </value>
                        <statement name="statement">
                           <block type="GrabObject" id="fF|#x`(B^@Vnec*.X5Dm">
                              <value name="objectType">
                                 <block type="Text" id="HR,r_,GSt7Qp@CXOrA76">
                                    <field name="text">Part_Cube</field>
                                 </block>
                              </value>
                              <value name="objectPosition">
                                 <block type="Text" id="1w~Zh5%xqu!r8QVf1$st">
                                    <field name="text">1</field>
                                 </block>
                              </value>
                           </block>
                        </statement>
                        <next>
                           <block type="Selection" id="g/yu;nq$PZOQM*V4#eAn">
                              <value name="condition">
                                 <block type="Text" id="|+[OoODO8PvDp1Ii!0g1">
                                    <field name="text">X&gt;1</field>
                                 </block>
                              </value>
                              <statement name="statement">
                                 <block type="GrabObject" id="@TR:|[C,T=yPEq;Vr_7Z">
                                    <value name="objectType">
                                       <block type="Text" id=".Jd[0|}eDE?6]vE!Hn(@">
                                          <field name="text">Part_Cylinder</field>
                                       </block>
                                    </value>
                                    <value name="objectPosition">
                                       <block type="Text" id="bcCC(dm0Y+-$fnaGWTFq">
                                          <field name="text">2</field>
                                       </block>
                                    </value>
                                 </block>
                              </statement>
                           </block>
                        </next>
                     </block>
                  </statement>
               </block>
            </next>
         </block>
      </next>
   </block>
</xml>